txtrpacker/__init__.py
txtrpacker/cli.py
txtrpacker/rect.py
txtrpacker/txtrpacker.py
txtrpacker-0.3.dist-info/AUTHORS.md
txtrpacker-0.3.dist-info/LICENSE
txtrpacker-0.3.dist-info/METADATA
txtrpacker-0.3.dist-info/WHEEL
txtrpacker-0.3.dist-info/entry_points.txt
txtrpacker-0.3.dist-info/top_level.txt
txtrpacker-0.3.dist-info/RECORD
