Metadata-Version: 2.1
Name: txtrpacker
Version: 0.3
Summary: Texture Packer
Home-page: https://github.com/brean/python-txtrpacker
Author: Andreas Bresser
License: BSD
License-File: LICENSE
License-File: AUTHORS.md
Requires-Dist: Pillow
